[
	{
			"id": 0,
			"brand": "Huawei",
			"category": "SmartWatch",
			"title": "Фитнес-браслет HUAWEI Band 6, зеленый",
			"description": {
					"Сенсорный экран: ": "Да",
					"Датчики: ": "Акселерометр, Гироскоп, Пульсометр",
					"Мониторинг: ": "Сна",
					"Защищенность: ": "Водонепроницаемость",
					"Время работы от аккумулятора, дни: ": "14"
			},
			"price": 145.55,
			"discount": 0,
			"currency": "BYN",
			"src": "https://cdn1.ozone.ru/s3/multimedia-m/wc250/6151153582.jpg",
			"isChoise": true,
			"count": 1
	},
	{
			"id": 1,
			"brand": "Huawei",
			"category": "SmartWatch",
			"title": "Фитнес-браслет HUAWEI Band 6, розовый",
			"description": {
					"Совместимость: ": "Android",
					"Сенсорный экран: ": "Да",
					"Датчики: ": "GPS-трекер",
					"Мониторинг: ": "Сна",
					"Защищенность: ": "Водонепроницаемость"
			},
			"price": 172.21,
			"discount": 0,
			"currency": "BYN",
			"src": "https://cdn1.ozone.ru/s3/multimedia-1/wc250/6151153597.jpg",
			"isChoise": true,
			"count": 1
	},
	{
			"id": 2,
			"brand": "Huawei",
			"category": "SmartWatch",
			"title": "Умные часы HUAWEI Watch Fit Elegant, черный",
			"description": {
					"Диагональ экрана, дюймы: ": "1.64",
					"Разрешение экрана: ": "456x280",
					"Беспроводные интерфейсы: ": "Bluetooth",
					"Совместимость: ": "Android, iOS",
					"Защита от влаги: ": "Да"
			},
			"price": 323.04,
			"discount": 0,
			"currency": "BYN",
			"src": "https://cdn1.ozone.ru/s3/multimedia-x/wc250/6083438997.jpg",
			"isChoise": true,
			"count": 1
	},
	{
			"id": 3,
			"brand": "Huawei",
			"category": "SmartWatch",
			"title": "Фитнес-браслет HUAWEI Band 6, черный",
			"description": {
					"Совместимость: ": "Android, iOS",
					"Сенсорный экран: ": "Да",
					"Мониторинг: ": "Сна",
					"Защищенность: ": "Водонепроницаемость",
					"Время работы от аккумулятора, дни: ": "14"
			},
			"price": 160.54,
			"discount": 0,
			"currency": "BYN",
			"src": "https://cdn1.ozone.ru/s3/multimedia-3/wc250/6151153671.jpg",
			"isChoise": true,
			"count": 1
	},
	{
			"id": 4,
			"brand": "Huawei",
			"category": "SmartWatch",
			"title": "Умные часы HUAWEI Watch GT 2 Pro, 46mm, туманно-серый",
			"description": {
					"Диагональ экрана, дюймы: ": "1.39",
					"Разрешение экрана: ": "454х454",
					"Беспроводные интерфейсы: ": "Bluetooth",
					"Совместимость: ": "Android",
					"Защита от влаги: ": "Да"
			},
			"price": 743.59,
			"discount": 0,
			"currency": "BYN",
			"src": "https://cdn1.ozone.ru/s3/multimedia-x/wc250/6083438961.jpg",
			"isChoise": true,
			"count": 1
	},
	{
			"id": 5,
			"brand": "Huawei",
			"category": "SmartWatch",
			"title": "Умные часы HUAWEI Watch GT 2, коричневый",
			"description": {
					"Диагональ экрана, дюймы: ": "1.4",
					"Разрешение экрана: ": "454х454",
					"Беспроводные интерфейсы: ": "Bluetooth, GPS",
					"Совместимость: ": "Android, iOS",
					"Защита от влаги: ": "Да"
			},
			"price": 472.93,
			"discount": 0,
			"currency": "BYN",
			"src": "https://cdn1.ozone.ru/s3/multimedia-j/wc250/6082570195.jpg",
			"isChoise": true,
			"count": 1
	},
	{
			"id": 6,
			"brand": "Huawei",
			"category": "SmartWatch",
			"title": "Фитнес-браслет HUAWEI Band 6, черный",
			"description": {
					"Совместимость: ": "Android, iOS",
					"Сенсорный экран: ": "Да",
					"Датчики: ": "GPS-трекер",
					"Мониторинг: ": "Сна",
					"Защищенность: ": "Водонепроницаемость"
			},
			"price": 147.91,
			"discount": 0,
			"currency": "BYN",
			"src": "https://cdn1.ozone.ru/s3/multimedia-q/wc250/6266745158.jpg",
			"isChoise": true,
			"count": 1
	},
	{
			"id": 7,
			"brand": "Huawei",
			"category": "SmartWatch",
			"title": "Умные часы HUAWEI WATCH Fit New TIA-B09, черный",
			"description": {
					"Диагональ экрана, дюймы: ": "1.64",
					"Разрешение экрана: ": "456x280",
					"Беспроводные интерфейсы: ": "Bluetooth, GPS",
					"Совместимость: ": "Android, iOS",
					"Защита от влаги: ": "Да"
			},
			"price": 298.08,
			"discount": 0,
			"currency": "BYN",
			"src": "https://cdn1.ozone.ru/s3/multimedia-g/wc250/6153002284.jpg",
			"isChoise": true,
			"count": 1
	},
	{
			"id": 8,
			"brand": "Huawei",
			"category": "SmartWatch",
			"title": "Умные часы HUAWEI WATCH 3 LTE 46 мм, черный",
			"description": {
					"Диагональ экрана, дюймы: ": "1.43",
					"Разрешение экрана: ": "466x466",
					"Беспроводные интерфейсы: ": "Bluetooth, Wi-Fi, GPS, NFC",
					"Совместимость: ": "Android, iOS",
					"Защита от влаги: ": "Да"
			},
			"price": 958.44,
			"discount": 0,
			"currency": "BYN",
			"src": "https://cdn1.ozone.ru/s3/multimedia-5/wc250/6091712993.jpg",
			"isChoise": true,
			"count": 1
	},
	{
			"id": 9,
			"brand": "Huawei",
			"category": "SmartWatch",
			"title": "Умные часы HUAWEI WATCH Fit , черный",
			"description": {
					"Диагональ экрана, дюймы: ": "1.64",
					"Разрешение экрана: ": "456x280",
					"Беспроводные интерфейсы: ": "Bluetooth, GPS",
					"Совместимость: ": "Android, iOS",
					"Защита от влаги: ": "Да"
			},
			"price": 286.87,
			"discount": 0,
			"currency": "BYN",
			"src": "https://cdn1.ozone.ru/s3/multimedia-6/wc250/6083438934.jpg",
			"isChoise": true,
			"count": 1
	},
	{
			"id": 10,
			"brand": "Huawei",
			"category": "SmartWatch",
			"title": "Умные часы HUAWEI Band 6, 38mm",
			"description": {
					"Диагональ экрана, дюймы: ": "1.47",
					"Совместимость: ": "Android, PC, Mac OS, Windows",
					"Защита от влаги: ": "Да",
					"Степень защиты: ": "IP69K",
					"Время работы от аккумулятора, дни: ": "14"
			},
			"price": 220.49,
			"discount": 0,
			"currency": "BYN",
			"src": "https://cdn1.ozone.ru/s3/multimedia-x/wc250/6273840117.jpg",
			"isChoise": true,
			"count": 1
	},
	{
			"id": 11,
			"brand": "Huawei",
			"category": "SmartWatch",
			"title": "Фитнес-браслет HUAWEI Band 6, зеленый",
			"description": {
					"Совместимость: ": "Android",
					"Сенсорный экран: ": "Да",
					"Датчики: ": "Акселерометр, Гироскоп, Пульсометр",
					"Мониторинг: ": "Физической активности",
					"Диагональ экрана, дюймы: ": "1.47"
			},
			"price": 145.94,
			"discount": 0,
			"currency": "BYN",
			"src": "https://cdn1.ozone.ru/s3/multimedia-4/wc250/6066534844.jpg",
			"isChoise": true,
			"count": 1
	},
	{
			"id": 12,
			"brand": "Huawei",
			"category": "SmartWatch",
			"title": "Умные часы HUAWEI Watch Kids 4 Pro, 41mm, розовый",
			"description": {
					"Диагональ экрана, дюймы: ": "1.41",
					"Разрешение экрана: ": "320x360",
					"Беспроводные интерфейсы: ": "Bluetooth, Wi-Fi",
					"Совместимость: ": "Android, iOS",
					"Защита от влаги: ": "Да"
			},
			"price": 433.49,
			"discount": 0,
			"currency": "BYN",
			"src": "https://cdn1.ozone.ru/s3/multimedia-d/wc250/6166965349.jpg",
			"isChoise": true,
			"count": 1
	},
	{
			"id": 13,
			"brand": "Huawei",
			"category": "SmartWatch",
			"title": "Умные часы HUAWEI Watch Fit Elegant, Белоснежный",
			"description": {
					"Диагональ экрана, дюймы: ": "1.64",
					"Разрешение экрана: ": "456x280",
					"Беспроводные интерфейсы: ": "Bluetooth",
					"Совместимость: ": "Android, iOS",
					"Защита от влаги: ": "Да"
			},
			"price": 444.29,
			"discount": 0,
			"currency": "BYN",
			"src": "https://cdn1.ozone.ru/s3/multimedia-s/wc250/6083440036.jpg",
			"isChoise": true,
			"count": 1
	},
	{
			"id": 14,
			"brand": "Huawei",
			"category": "SmartWatch",
			"title": "Умные часы HUAWEI Watch GT 2 Sport (LTN-B19) (Категория \"A\". См. описание), 46mm",
			"description": {
					"Разрешение экрана: ": "454х454",
					"Беспроводные интерфейсы: ": "Bluetooth",
					"Совместимость: ": "Android, iOS",
					"Время работы от аккумулятора, дни: ": "14",
					"Технология матрицы: ": "AMOLED"
			},
			"price": 474.82,
			"discount": 0,
			"currency": "BYN",
			"src": "https://cdn1.ozone.ru/s3/multimedia-8/wc250/6272785832.jpg",
			"isChoise": true,
			"count": 1
	},
	{
			"id": 15,
			"brand": "Huawei",
			"category": "SmartWatch",
			"title": "Умные часы HUAWEI Watch GT 3 Classic, 46mm, серебристый, коричневый",
			"description": {
					"Диагональ экрана, дюймы: ": "1.32",
					"Разрешение экрана: ": "466x466",
					"Беспроводные интерфейсы: ": "Bluetooth, NFC, GPS",
					"Совместимость: ": "Android, iOS",
					"Защита от влаги: ": "Да"
			},
			"price": 906.81,
			"discount": 0,
			"currency": "BYN",
			"src": "https://cdn1.ozone.ru/s3/multimedia-w/wc250/6286926872.jpg",
			"isChoise": true,
			"count": 1
	},
	{
			"id": 16,
			"brand": "Huawei",
			"category": "SmartWatch",
			"title": "Умные часы HUAWEI Watch GT 2 Sport (LTN-B19) (Категория \"A\". См. описание), 46mm",
			"description": {
					"Разрешение экрана: ": "454х454",
					"Беспроводные интерфейсы: ": "Bluetooth",
					"Совместимость: ": "Android, iOS",
					"Защита от влаги: ": "Да",
					"Время работы от аккумулятора, дни: ": "14"
			},
			"price": 474.82,
			"discount": 0,
			"currency": "BYN",
			"src": "https://cdn1.ozone.ru/s3/multimedia-f/wc250/6172379211.jpg",
			"isChoise": true,
			"count": 1
	},
	{
			"id": 17,
			"brand": "Huawei",
			"category": "SmartWatch",
			"title": "Умные часы HUAWEI WATCH GT Runner, черный, 46mm",
			"description": {
					"Диагональ экрана, дюймы: ": "1.43",
					"Разрешение экрана: ": "466x466",
					"Беспроводные интерфейсы: ": "GPS, Bluetooth",
					"Совместимость: ": "Android, iOS",
					"Защита от влаги: ": "Да"
			},
			"price": 689.87,
			"discount": 0,
			"currency": "BYN",
			"src": "https://cdn1.ozone.ru/s3/multimedia-7/wc250/6160233199.jpg",
			"isChoise": true,
			"count": 1
	},
	{
			"id": 18,
			"brand": "Huawei",
			"category": "SmartWatch",
			"title": "Фитнес-браслет HUAWEI Band 6, черный",
			"description": {
					"Совместимость: ": "Android, iOS",
					"Сенсорный экран: ": "Да",
					"Мониторинг: ": "Сна",
					"Защищенность: ": "Водонепроницаемость",
					"Время работы от аккумулятора, дни: ": "14"
			},
			"price": 149.41,
			"discount": 0,
			"currency": "BYN",
			"src": "https://cdn1.ozone.ru/s3/multimedia-3/wc250/6151153671.jpg",
			"isChoise": true,
			"count": 1
	},
	{
			"id": 19,
			"brand": "Huawei",
			"category": "SmartWatch",
			"title": "Умные часы HUAWEI WATCH GT3 Jupiter, 46mm, черный",
			"description": {
					"Диагональ экрана, дюймы: ": "1.43",
					"Разрешение экрана: ": "466x466",
					"Беспроводные интерфейсы: ": "GPS, Bluetooth",
					"Совместимость: ": "Android, iOS",
					"Защита от влаги: ": "Да"
			},
			"price": 764.38,
			"discount": 0,
			"currency": "BYN",
			"src": "https://cdn1.ozone.ru/s3/multimedia-1/wc250/6160233085.jpg",
			"isChoise": true,
			"count": 1
	}
]